{
  "project_info": {
    "project_number": "570371922304",
    "project_id": "otp-firebase-b04ba",
    "storage_bucket": "otp-firebase-b04ba.appspot.com"
  },
  "client": [
    {
      "client_info": {
        "mobilesdk_app_id": "1:570371922304:android:42ba8292dc8e55430cc965",
        "android_client_info": {
          "package_name": "com.example.otp_auth"
        }
      },
      "oauth_client": [
        {
          "client_id": "570371922304-r60c0sp8rbb9i5fvu0rljvn25g86s2p4.apps.googleusercontent.com",
          "client_type": 1,
          "android_info": {
            "package_name": "com.example.otp_auth",
            "certificate_hash": "561b01599c3cc8bd8e095f3f3b97f8b537710694"
          }
        },
        {
          "client_id": "570371922304-hvfgc4g6gan1gec4846luvj8sh21rj4p.apps.googleusercontent.com",
          "client_type": 3
        }
      ],
      "api_key": [
        {
          "current_key": "AIzaSyB3j-21lo51bYD0o7ODQy69txtZR-GE-2I"
        }
      ],
      "services": {
        "appinvite_service": {
          "other_platform_oauth_client": [
            {
              "client_id": "570371922304-hvfgc4g6gan1gec4846luvj8sh21rj4p.apps.googleusercontent.com",
              "client_type": 3
            }
          ]
        }
      }
    }
  ],
  "configuration_version": "1"
}